nonebot_plugin_nekoimage/Matchers/__init__.py
nonebot_plugin_nekoimage/Matchers/searchMatcher.py
nonebot_plugin_nekoimage/Models/config.py
nonebot_plugin_nekoimage/Models/request.py
nonebot_plugin_nekoimage/Models/response.py
nonebot_plugin_nekoimage/Services/searchService.py
nonebot_plugin_nekoimage/Utils/extraLogic.py
nonebot_plugin_nekoimage/__init__.py
nonebot_plugin_nekoimage-0.3.3.dist-info/METADATA
nonebot_plugin_nekoimage-0.3.3.dist-info/WHEEL
nonebot_plugin_nekoimage-0.3.3.dist-info/RECORD
