Metadata-Version: 2.1
Name: nonebot-plugin-nekoimage
Version: 0.3.3
Summary: A nonebot plugin for integrating with NekoImageGallery
Home-page: https://github.com/pk5ls20/nonebot-plugin-nekoimage
License: AGPL-3.0
Keywords: nonebot,nonebot2
Author: pk5ls20
Author-email: pk5ls20@outlook.com
Requires-Python: >=3.9,<4.0
Classifier: License :: OSI Approved :: GNU Affero General Public License v3
Classifier: Programming Language :: Python :: 3
Classifier: Programming Language :: Python :: 3.9
Classifier: Programming Language :: Python :: 3.10
Classifier: Programming Language :: Python :: 3.11
Classifier: Programming Language :: Python :: 3.12
Requires-Dist: httpx
Requires-Dist: nonebot-adapter-onebot (>=2.0.0-beta.1,<3.0.0)
Requires-Dist: nonebot-adapter-qq (>=1.3.5,<2.0.0)
Requires-Dist: nonebot-plugin-send-anything-anywhere (>=0.4.0,<0.5.0)
Requires-Dist: nonebot2 (>=2.0.0,<3.0.0)
Requires-Dist: pydantic
Requires-Dist: pytz
Project-URL: Documentation, https://github.com/pk5ls20/nonebot-plugin-nekoimage/wiki
Project-URL: Repository, https://github.com/pk5ls20/nonebot-plugin-nekoimage
